{
  "systems": [
    {
      "id": "erp",
      "name": "ERP System",
      "color": "#e74c3c",
      "x": 400,
      "y": 250
    },
    {
      "id": "crm",
      "name": "NTI FM",
      "color": "#e91e63",
      "x": 200,
      "y": 150
    },
    {
      "id": "webshop",
      "name": "Webshop",
      "color": "#2ecc71",
      "x": 620,
      "y": 150
    },
    {
      "id": "bi",
      "name": "BI / Rapportering",
      "color": "#f39c12",
      "x": 400,
      "y": 430
    },
    {
      "id": "wms",
      "name": "WMS / Lager",
      "color": "#9b59b6",
      "x": 650,
      "y": 380
    },
    {
      "id": "email",
      "name": "NTI Vedligehold",
      "color": "#e91e63",
      "x": 160,
      "y": 360
    }
  ],
  "connections": [
    {
      "from": "erp",
      "to": "crm",
      "direction": "both"
    },
    {
      "from": "erp",
      "to": "webshop",
      "direction": "from"
    },
    {
      "from": "erp",
      "to": "bi",
      "direction": "to"
    },
    {
      "from": "erp",
      "to": "wms",
      "direction": "both"
    },
    {
      "from": "crm",
      "to": "email",
      "direction": "from"
    },
    {
      "from": "webshop",
      "to": "wms",
      "direction": "to"
    }
  ]
}